[
    {
        "key": "1551108523261a8949e54f4f4f8d743bfc7ac928b2",
        "sender": "tenant_1548260788438514e9059846d0ba16d3d0e0ed5778",
        "sender_name": "Studentkortet",
        "created_at": "2019-02-25",
        "generated_at": "2019-02-25T15:28:43Z",
        "subject": "Content with link",
        "status": "read",
        "labels": {
            "agreement": false,
            "paid": false,
            "trashed": false,
            "viewed": true,
            "seen": true
        },
        "indexed_at": "2019-03-27T12:44:54Z",
        "payable": false,
        "amount": null,
        "currency": null,
        "payment_status": null,
        "pay_date": null,
        "due_date": null,
        "agreement_key": null,
        "agreement_status": null,
        "variable_amount": false
    },
    {
        "key": "15500636587cbe37ff79fc4a14bab979f528818b82",
        "sender": "tenant_13944464250573ba9cbb8f4cb5a6b92f28c96b6712",
        "sender_name": "Brevo",
        "created_at": "2019-02-13T13:14:18Z",
        "generated_at": "2019-02-13T13:14:17Z",
        "subject": "sun is coming to Sthlm",
        "status": "unread",
        "labels": {
            "agreement": false,
            "paid": false,
            "trashed": false,
            "viewed": false,
            "seen": true
        },
        "indexed_at": "2019-03-27T11:37:50Z",
        "payable": false,
        "amount": null,
        "currency": null,
        "payment_status": null,
        "pay_date": null,
        "due_date": null,
        "agreement_key": null,
        "agreement_status": null,
        "variable_amount": false
    },
    {
        "key": "15531763604ea2d5fec2504c7ea81e0f6467b46f23",
        "sender": "tenant_1341573157b3a1c55f220f4007b2e44789d2d04015",
        "sender_name": "Kivra",
        "created_at": "2019-03-21T13:52:40Z",
        "generated_at": "2019-03-21T13:52:40Z",
        "subject": "Variable amount",
        "status": "read",
        "labels": {
            "agreement": false,
            "paid": false,
            "trashed": false,
            "viewed": true,
            "seen": true
        },
        "indexed_at": "2019-03-29T14:34:08Z",
        "payable": true,
        "amount": "500",
        "currency": "SEK",
        "payment_status": "unpaid",
        "pay_date": null,
        "due_date": "2019-05-28T00:00:00Z",
        "agreement_key": null,
        "agreement_status": null,
        "variable_amount": true
    },
    {
        "key": "15531763604ea2d5fec2504c7ea81e0f6467b46f26",
        "sender": "tenant_1341573157b3a1c55f220f4007b2e44789d2d04015",
        "sender_name": "Kivra",
        "created_at": "2019-03-21T13:52:40Z",
        "generated_at": "2019-03-21T13:52:40Z",
        "subject": "Non variable amount",
        "status": "read",
        "labels": {
            "agreement": false,
            "paid": false,
            "trashed": false,
            "viewed": true,
            "seen": true
        },
        "indexed_at": "2019-03-29T14:34:08Z",
        "payable": true,
        "amount": "25000",
        "currency": "SEK",
        "payment_status": "unpaid",
        "pay_date": null,
        "due_date": "2019-05-28T00:00:00Z",
        "agreement_key": null,
        "agreement_status": null,
        "variable_amount": false
    },
    {
        "key": "15531763604ea2d5fec2504c7ea81e0f6467b46f25",
        "sender": "tenant_1341573157b3a1c55f220f4007b2e44789d2d04015",
        "sender_name": "Kivra",
        "created_at": "2019-03-22T13:52:40Z",
        "generated_at": "2019-03-21T13:52:40Z",
        "subject": "Variable amount with input amount",
        "status": "read",
        "labels": {
            "agreement": false,
            "paid": false,
            "trashed": false,
            "viewed": true,
            "seen": true
        },
        "indexed_at": "2019-03-29T14:34:08Z",
        "payable": true,
        "amount": "4000",
        "currency": "SEK",
        "payment_status": "pending",
        "pay_date": null,
        "due_date": "2019-05-29T00:00:00Z",
        "input_amount": "500.00",
        "agreement_key": null,
        "agreement_status": null,
        "variable_amount": true
    },
    {
        "key": "15531763604ea2d5fec2504c7ea81e0f6467b46fx2",
        "sender": "tenant_1341573157b3a1c55f220f4007b2e44789d2d04015",
        "sender_name": "Kivra",
        "created_at": "2019-03-22T13:52:40Z",
        "generated_at": "2019-03-21T13:52:40Z",
        "subject": "Non variable amount with input amount",
        "status": "read",
        "labels": {
            "agreement": false,
            "paid": false,
            "trashed": false,
            "viewed": true,
            "seen": true
        },
        "indexed_at": "2019-03-29T14:34:08Z",
        "payable": true,
        "amount": "4000",
        "currency": "SEK",
        "payment_status": "pending",
        "pay_date": null,
        "due_date": "2019-05-29T00:00:00Z",
        "input_amount": "500.00",
        "agreement_key": null,
        "agreement_status": null,
        "variable_amount": true
    },
    {
        "key": "15531763604ea2d5fec2504c7ea81e0f6467b46f26",
        "sender": "tenant_1341573157b3a1c55f220f4007b2e44789d2d04015",
        "sender_name": "Kivra",
        "created_at": "2019-03-22T13:52:40Z",
        "generated_at": "2019-03-21T13:52:40Z",
        "subject": "Variable amount without input amount",
        "status": "read",
        "labels": {
            "agreement": false,
            "paid": false,
            "trashed": false,
            "viewed": true,
            "seen": true
        },
        "indexed_at": "2019-03-29T14:34:08Z",
        "payable": true,
        "amount": "4000",
        "currency": "SEK",
        "payment_status": "pending",
        "pay_date": null,
        "due_date": "2019-05-29T00:00:00Z",
        "agreement_key": null,
        "agreement_status": null,
        "variable_amount": true
    },
    {
        "key": "15531763604ea2d5fec2504c7ea81e0f6467b46f30",
        "sender": "tenant_1341573157b3a1c55f220f4007b2e44789d2d04015",
        "sender_name": "Kivra",
        "created_at": "2019-03-22T13:52:40Z",
        "generated_at": "2019-03-21T13:52:40Z",
        "subject": "Non variable amount",
        "status": "read",
        "labels": {
            "agreement": false,
            "paid": false,
            "trashed": false,
            "viewed": true,
            "seen": true
        },
        "indexed_at": "2019-03-29T14:34:08Z",
        "payable": true,
        "amount": "4000",
        "currency": "SEK",
        "payment_status": "pending",
        "pay_date": null,
        "due_date": "2019-05-29T00:00:00Z",
        "agreement_key": null,
        "agreement_status": null,
        "variable_amount": false
    },
    {
        "key": "15531763604ea2d5fec2504c7ea81e0f6467b46f2s",
        "sender": "tenant_1341573157b3a1c55f220f4007b2e44789d2d04015",
        "sender_name": "Kivra",
        "created_at": "2019-03-21T13:52:40Z",
        "generated_at": "2019-03-21T13:52:40Z",
        "subject": "Payment with mapped content item",
        "status": "read",
        "labels": {
            "agreement": false,
            "paid": true,
            "trashed": false,
            "viewed": true,
            "seen": true
        },
        "indexed_at": "2019-03-29T14:34:08Z",
        "payable": true,
        "amount": "2500",
        "currency": "SEK",
        "payment_status": "paid",
        "pay_date": "2019-09-20T00:00:00Z",
        "due_date": "2019-09-20T00:00:00Z",
        "agreement_key": null,
        "agreement_status": null,
        "input_amount": "2499.00",
        "variable_amount": true
    },
    {
        "key": "15420313745f3f150ce81f4bdaa0ee6d01538d3ee0",
        "sender": "user_14228736678bf773c75fea4020bf6bf6f219cba391",
        "sender_name": "Bop Thelin",
        "created_at": "2018-11-12T14:02:54Z",
        "generated_at": "2018-11-12T14:02:54Z",
        "subject": "ångerrätt",
        "status": "read",
        "labels": {
            "agreement": true,
            "paid": false,
            "trashed": false,
            "viewed": true
        },
        "indexed_at": "2018-11-14T12:14:28Z",
        "payable": false,
        "amount": null,
        "currency": null,
        "payment_status": null,
        "pay_date": null,
        "due_date": null,
        "agreement_key": "154203137420cb6b7538814bf789ab126011da74ae",
        "agreement_status": "in_progress",
        "variable_amount": false
    },
    {
        "key": "15531763604ea2d5fec2504c7ea81e0f6467b46f30",
        "sender": "tenant_1341573157b3a1c55f220f4007b2e44789d2d04015",
        "sender_name": "Kivra",
        "created_at": "2019-03-21T13:52:40Z",
        "generated_at": "2019-03-21T13:52:40Z",
        "subject": "Faktura 02",
        "status": "read",
        "labels": {
            "agreement": false,
            "paid": true,
            "trashed": false,
            "viewed": true,
            "seen": true
        },
        "indexed_at": "2019-03-29T14:34:08Z",
        "payable": true,
        "amount": "699",
        "currency": "SEK",
        "payment_status": "paid",
        "pay_date": "2019-05-28T00:00:00Z",
        "due_date": "2019-05-28T00:00:00Z",
        "agreement_key": null,
        "agreement_status": null,
        "input_amount": "210",
        "variable_amount": true
    },
    {
        "key": "15531763604ea2d5fec2504c7ea81e0f6467b46fg3",
        "sender": "tenant_1341573157b3a1c55f220f4007b2e44789d2d04015",
        "sender_name": "Kivra",
        "created_at": "2019-03-21T13:52:40Z",
        "generated_at": "2019-03-21T13:52:40Z",
        "subject": "Marked as paid",
        "status": "read",
        "labels": {
            "agreement": false,
            "paid": true,
            "trashed": false,
            "viewed": true,
            "seen": true
        },
        "indexed_at": "2019-03-29T14:34:08Z",
        "payable": true,
        "amount": "699",
        "currency": "SEK",
        "payment_status": "unpaid",
        "pay_date": "2019-05-28T00:00:00Z",
        "due_date": "2019-05-28T00:00:00Z",
        "agreement_key": null,
        "agreement_status": null,
        "input_amount": "210",
        "variable_amount": true
    },
    {
        "key": "15531763604ea2d5fec2504c7ea81e0f6467b46f28",
        "sender": "tenant_1341573157b3a1c55f220f4007b2e44789d2d04015",
        "sender_name": "Kivra",
        "created_at": "2019-03-21T13:52:40Z",
        "generated_at": "2019-03-21T13:52:40Z",
        "subject": "Payment with mapped content item",
        "status": "read",
        "labels": {
            "agreement": false,
            "paid": true,
            "trashed": false,
            "viewed": true,
            "seen": true
        },
        "indexed_at": "2019-03-29T14:34:08Z",
        "payable": true,
        "amount": "500",
        "currency": "SEK",
        "payment_status": "paid",
        "pay_date": "2019-05-28T00:00:00Z",
        "due_date": "2019-05-28T00:00:00Z",
        "agreement_key": null,
        "agreement_status": null,
        "input_amount": "29",
        "variable_amount": true
    },
    {
        "key": "15531763604ea2d5fec2504c7ea81e0f6467b46f29",
        "sender": "tenant_1341573157b3a1c55f220f4007b2e44789d2d04015",
        "sender_name": "Kivra",
        "created_at": "2019-03-21T13:52:40Z",
        "generated_at": "2019-03-21T13:52:40Z",
        "subject": "Payment with mapped content item",
        "status": "read",
        "labels": {
            "agreement": false,
            "paid": false,
            "trashed": false,
            "viewed": true,
            "seen": true
        },
        "indexed_at": "2019-03-29T14:34:08Z",
        "payable": true,
        "amount": "69000",
        "currency": "SEK",
        "payment_status": "paid",
        "pay_date": "2019-05-28T00:00:00Z",
        "due_date": "2019-05-28T00:00:00Z",
        "agreement_key": null,
        "agreement_status": null,
        "input_amount": "69000",
        "variable_amount": true
    },
    {
        "key": "15531763604ea2d5fec2504c7ea81e0f6467b46f2a",
        "sender": "tenant_1341573157b3a1c55f220f4007b2e44789d2d04015",
        "sender_name": "Kivra",
        "created_at": "2019-03-21T13:52:40Z",
        "generated_at": "2019-03-21T13:52:40Z",
        "subject": "Pacioli down single content item",
        "status": "read",
        "labels": {
            "agreement": false,
            "paid": true,
            "trashed": false,
            "viewed": true,
            "seen": true
        },
        "indexed_at": "2019-03-29T14:34:08Z",
        "payable": true,
        "amount": "2530",
        "currency": "SEK",
        "payment_status": "paid",
        "pay_date": "2019-07-28T00:00:00Z",
        "due_date": "2019-07-28T00:00:00Z",
        "agreement_key": null,
        "agreement_status": null,
        "input_amount": "2000",
        "variable_amount": true
    },
]
